pyDBoW3-0.2.data/purelib/pyDBoW3/__init__.py
pyDBoW3-0.2.data/purelib/pyDBoW3/opencv_world400.dll
pyDBoW3-0.2.data/purelib/pyDBoW3/pyDBoW3.pyd
pyDBoW3-0.2.dist-info/METADATA
pyDBoW3-0.2.dist-info/WHEEL
pyDBoW3-0.2.dist-info/top_level.txt
pyDBoW3-0.2.dist-info/RECORD
