Metadata-Version: 2.1
Name: pyDBoW3
Version: 0.2
Summary: Python wrappers for DBoW3 library.
Home-page: http://github.com/foxis/pyDBoW3
Author: Andrius Mikonis
Author-email: andrius.mikonis@gmail.com
License: MIT
Keywords: bag of words bow dbow3 dbow slam orb odometry visual
Platform: UNKNOWN
Classifier: Development Status :: 3 - Alpha
Classifier: License :: OSI Approved :: MIT License
Classifier: Programming Language :: Python :: 2.7
Classifier: Programming Language :: Python :: 3.5
Classifier: Programming Language :: Python :: 3.6
Classifier: Programming Language :: Python :: 3.7
Classifier: Topic :: Text Processing :: Linguistic
Requires-Dist: numpy
